gott/__init__.py
gott/function.py
gott-0.0.2.dist-info/LICENSE
gott-0.0.2.dist-info/METADATA
gott-0.0.2.dist-info/WHEEL
gott-0.0.2.dist-info/top_level.txt
gott-0.0.2.dist-info/RECORD
